django_api_proxy/__init__.py
django_api_proxy/adapters.py
django_api_proxy/settings.py
django_api_proxy/utils.py
django_api_proxy/views.py
django_api_proxy-0.1.1.dist-info/LICENSE
django_api_proxy-0.1.1.dist-info/METADATA
django_api_proxy-0.1.1.dist-info/WHEEL
django_api_proxy-0.1.1.dist-info/top_level.txt
django_api_proxy-0.1.1.dist-info/RECORD
