Metadata-Version: 2.1
Name: django-api-proxy
Version: 0.1.1
Summary: Django Rest Framework proxy API
Home-page: https://github.com/aiselis/django-api-proxy
Author: Alessio Pinna
Author-email: alessio.pinna@aiselis.com
Maintainer: Alessio Pinna <alessio.pinna@aiselis.com>
License: BSD
Project-URL: Bug Reports, https://github.com/aiselis/django-api-proxy/issues
Project-URL: Source, https://github.com/aiselis/django-api-proxy
Platform: UNKNOWN
Classifier: License :: OSI Approved :: BSD License
Classifier: Intended Audience :: Developers
Classifier: Programming Language :: Python
Classifier: Programming Language :: Python :: 3
Classifier: Programming Language :: Python :: 3.7
Classifier: Programming Language :: Python :: 3.8
Classifier: Programming Language :: Python :: 3.9
Classifier: Programming Language :: Python :: 3.10
Classifier: Development Status :: 4 - Beta
Classifier: Operating System :: OS Independent
Classifier: Framework :: Django
Classifier: Framework :: Django :: 3
Classifier: Framework :: Django :: 4
Requires-Python: >=3.7
License-File: LICENSE
Requires-Dist: django (>=3.0)
Requires-Dist: requests (>=2.10)
Requires-Dist: djangorestframework (>=3.1)
Requires-Dist: urllib3 (>=1.20)
Requires-Dist: six (>=1.10)
